{"backgroundColor": [130, 206, 181], "ballList": [{"ballSize": [15, 10], "color": [255, 0, 0], "displayMessage": false, "displayTrail": true, "id": 0, "message": "No", "sound": "c:\\Users\\Barry\\Documents\\search_in_pi\\BallFall\\sounds\\Ball_sounds\\No.mp3", "soundVolume": 1.0, "trailLenght": 15, "velocity": [-6.0, 2.0]}, {"ballSize": [15, 10], "color": [0, 255, 0], "displayMessage": false, "displayTrail": true, "id": 1, "message": "Yes", "sound": "c:\\Users\\Barry\\Documents\\search_in_pi\\BallFall\\sounds\\Ball_sounds\\Yes.mp3", "soundVolume": 0.4, "trailLenght": 15, "velocity": [7.0, 1.0]}], "ballSize": [15, 10], "displayScore": true, "displayTrails": true, "haloColor": [255, 255, 255], "message": "Are you dumb ?", "midiFile": null, "minRadius": 175, "scoreMultiplier": 1, "screenSize": [540.0, 960.0], "spacingHalo": 15, "time": 57, "trailsLenght": 15, "widthHalo": 5}